apikeyclient/__init__.py
datadiensten_apikeyclient-0.6.0.dist-info/METADATA
datadiensten_apikeyclient-0.6.0.dist-info/WHEEL
datadiensten_apikeyclient-0.6.0.dist-info/top_level.txt
datadiensten_apikeyclient-0.6.0.dist-info/RECORD
