Metadata-Version: 2.1
Name: datadiensten-apikeyclient
Version: 0.6.0
Summary: Client for Datadiensten apikeyserv
Project-URL: Homepage, https://github.com/Amsterdam/apikeyserv
Requires-Dist: pause >=0.3
Requires-Dist: requests
Requires-Dist: PyJWT[crypto] ==2.8.0
Requires-Dist: build
Provides-Extra: dev
Requires-Dist: build ; extra == 'dev'
Requires-Dist: twine ; extra == 'dev'
Provides-Extra: test
Requires-Dist: requests-mock ; extra == 'test'
